clark/__init__.py
clark/__version__.py
clark/aws.py
clark/backend.py
clark/cache.py
clark/directory.py
clark/execution.py
clark/executor.py
clark/mac_executor.py
clark/main.py
clark/xnix_executor.py
clark_cli-0.4.5.dist-info/LICENSE
clark_cli-0.4.5.dist-info/METADATA
clark_cli-0.4.5.dist-info/WHEEL
clark_cli-0.4.5.dist-info/entry_points.txt
clark_cli-0.4.5.dist-info/top_level.txt
clark_cli-0.4.5.dist-info/RECORD
