Metadata-Version: 2.1
Name: clark-cli
Version: 0.4.5
Summary: A tool which auto-documents researcher workflows.
Home-page: https://github.com/Elio-Earth/clark-cli
Author: Elio Engineering
Author-email: tech@elio.earth
License: GPLv3
Platform: UNKNOWN
Classifier: Development Status :: 4 - Beta
Classifier: Intended Audience :: Science/Research
Classifier: Operating System :: MacOS
Classifier: Operating System :: POSIX
Classifier: Programming Language :: Python :: 3
Classifier: License :: OSI Approved :: GNU General Public License v3 (GPLv3)
Requires-Python: >=3.6.0
License-File: LICENSE
Requires-Dist: click (>=8.0.1)
Requires-Dist: requests (>=2.26.0)
Requires-Dist: boto3 (>=1.20.0)
Requires-Dist: colorama (>=0.4.4)
